AuditModule/__init__.py
AuditModule/common/AppConfigurations.py
AuditModule/common/AppConstants.py
AuditModule/common/__init__.py
AuditModule/common/configuration_settings.py
AuditModule/core/__init__.py
AuditModule/core/applications/Annotations.py
AuditModule/core/applications/AuditManagement.py
AuditModule/core/applications/AuditManagementModules.py
AuditModule/core/applications/AuditUserManagementStrategies.py
AuditModule/core/applications/__init__.py
AuditModule/core/persistences/PersistenceAdaptor.py
AuditModule/core/persistences/__init__.py
AuditModule/core/persistences/adaptors/CassandraPersistenceAdaptor.py
AuditModule/core/persistences/adaptors/__init__.py
AuditModule/core/services/__init__.py
AuditModule/core/services/audit_service.py
AuditModule/util/CommonUtils.py
AuditModule/util/LoggerUtil.py
AuditModule/util/Logging.py
AuditModule/util/__init__.py
conf/__init__.py
logs/__init__.py
upload/__init__.py
upload/__root__.py
KL_Audit_supportV1.9-1.0.dist-info/METADATA
KL_Audit_supportV1.9-1.0.dist-info/WHEEL
KL_Audit_supportV1.9-1.0.dist-info/top_level.txt
KL_Audit_supportV1.9-1.0.dist-info/RECORD
